kinneyotp/__init__.py
kinneyotp-0.0.17.dist-info/LICENSE
kinneyotp-0.0.17.dist-info/METADATA
kinneyotp-0.0.17.dist-info/WHEEL
kinneyotp-0.0.17.dist-info/top_level.txt
kinneyotp-0.0.17.dist-info/RECORD
